colorbridge/__init__.py
colorbridge/__main__.py
colorbridge/_path_config.py
colorbridge/cli.py
colorbridge/inc/1.png
colorbridge-2.1.18.data/data/share/applications/colorbridge.desktop
colorbridge-2.1.18.data/data/share/colorbridge/colorbridge_launcher.sh
colorbridge-2.1.18.dist-info/licenses/LICENSE
core/__init__.py
core/colorbridge_debug_logger.py
core/colorbridge_device_info_manager.py
core/colorbridge_environment_manager.py
core/colorbridge_error_recovery.py
core/colorbridge_log_analyzer.py
core/colorbridge_log_protector.py
core/colorbridge_logger_manager.py
core/colorbridge_message_processor.py
core/colorbridge_monitoring_system.py
core/colorbridge_serial_manager.py
core/colorbridge_terminal_logger.py
games/__init__.py
games/billiard_3d/__init__.py
games/billiard_3d/core.py
games/billiard_3d/ui.py
ui/__init__.py
ui/colorbridge_main_window.py
ui/colorbridge_notification_manager.py
ui/colorbridge_settings_dialog.py
ui/colorbridge_theme_manager.py
colorbridge-2.1.18.dist-info/METADATA
colorbridge-2.1.18.dist-info/WHEEL
colorbridge-2.1.18.dist-info/entry_points.txt
colorbridge-2.1.18.dist-info/top_level.txt
colorbridge-2.1.18.dist-info/RECORD
