Metadata-Version: 2.4
Name: colorbridge
Version: 2.1.18
Summary: 🌈 ColorBridge - AI8051U串口助手，半透明多巴胺配色串口调试工具
Home-page: https://atomgit.com/H076lik/ColorBridge
Author: 076lik
Author-email: 076lik <m17859782086_1@163.com>
License-Expression: GPL-3.0-only
Project-URL: Homepage, https://atomgit.com/H076lik/ColorBridge
Project-URL: Repository, https://atomgit.com/H076lik/ColorBridge.git
Project-URL: Issues, https://atomgit.com/H076lik/ColorBridge/issues
Keywords: serial,uart,ai8051u,usb-cdc,debug,embedded,hardware
Platform: Windows
Platform: Linux
Platform: macOS
Classifier: Development Status :: 4 - Beta
Classifier: Intended Audience :: Developers
Classifier: Topic :: Software Development :: Embedded Systems
Classifier: Programming Language :: Python :: 3
Classifier: Programming Language :: Python :: 3.8
Classifier: Programming Language :: Python :: 3.9
Classifier: Programming Language :: Python :: 3.10
Classifier: Programming Language :: Python :: 3.11
Classifier: Programming Language :: Python :: 3.12
Classifier: Operating System :: Microsoft :: Windows
Classifier: Operating System :: POSIX :: Linux
Classifier: Operating System :: MacOS :: MacOS X
Requires-Python: >=3.8
License-File: LICENSE
Requires-Dist: PyQt6>=6.6.0
Requires-Dist: pyserial>=3.5
Requires-Dist: python-dateutil>=2.8.2
Requires-Dist: psutil>=7.0.0
Provides-Extra: dev
Requires-Dist: pytest>=7.0; extra == "dev"
Requires-Dist: black>=22.0; extra == "dev"
Requires-Dist: flake8>=5.0; extra == "dev"
Requires-Dist: mypy>=1.0; extra == "dev"
Dynamic: author
Dynamic: home-page
Dynamic: license-file
Dynamic: platform
Dynamic: requires-python
